neoscale/__init__.py
neoscale/add.py
neoscale-24.0.1.2.dist-info/LICENSE
neoscale-24.0.1.2.dist-info/METADATA
neoscale-24.0.1.2.dist-info/WHEEL
neoscale-24.0.1.2.dist-info/top_level.txt
neoscale-24.0.1.2.dist-info/RECORD
