Metadata-Version: 2.1
Name: neoscale
Version: 24.0.1.2
Summary: Python SDK for MatrixDC NeoScale
Author-email: Author <wanglei@matrixorigin.com>
Project-URL: Homepage, https://github.com/matrixorigin/mdc-neoscale
Project-URL: Bug Tracker, https://github.com/matrixorigin/mdc-neoscale/issues
Classifier: Programming Language :: Python :: 3
Classifier: License :: OSI Approved :: Apache Software License
Classifier: Operating System :: OS Independent
Requires-Python: >=3.8
License-File: LICENSE
